parsomics_core/__init__.py
parsomics_core/configuration.py
parsomics_core/entities/__init__.py
parsomics_core/entities/files/__init__.py
parsomics_core/entities/files/drep/__init__.py
parsomics_core/entities/files/drep/directory/models.py
parsomics_core/entities/files/drep/directory/transactions.py
parsomics_core/entities/files/drep/entry/models.py
parsomics_core/entities/files/drep/entry/transactions.py
parsomics_core/entities/files/drep/parser.py
parsomics_core/entities/files/drep/validated_directory.py
parsomics_core/entities/files/fasta/__init__.py
parsomics_core/entities/files/fasta/entry/models.py
parsomics_core/entities/files/fasta/entry/transactions.py
parsomics_core/entities/files/fasta/file/models.py
parsomics_core/entities/files/fasta/file/transactions.py
parsomics_core/entities/files/fasta/file_factory.py
parsomics_core/entities/files/fasta/parser.py
parsomics_core/entities/files/fasta/sequence_type.py
parsomics_core/entities/files/fasta/validated_file.py
parsomics_core/entities/files/file_factory.py
parsomics_core/entities/files/gene_annotation/__init__.py
parsomics_core/entities/files/gene_annotation/_helpers.py
parsomics_core/entities/files/gene_annotation/entry/models.py
parsomics_core/entities/files/gene_annotation/entry/transactions.py
parsomics_core/entities/files/gene_annotation/file/models.py
parsomics_core/entities/files/gene_annotation/file/transactions.py
parsomics_core/entities/files/gff/__init__.py
parsomics_core/entities/files/gff/entry/models.py
parsomics_core/entities/files/gff/entry/transactions.py
parsomics_core/entities/files/gff/file/models.py
parsomics_core/entities/files/gff/file/transactions.py
parsomics_core/entities/files/gff/file_factory.py
parsomics_core/entities/files/gff/parser.py
parsomics_core/entities/files/gff/validated_file.py
parsomics_core/entities/files/gtdbtk/__init__.py
parsomics_core/entities/files/gtdbtk/entry/models.py
parsomics_core/entities/files/gtdbtk/entry/transactions.py
parsomics_core-4.1.1.dist-info/LICENSE
parsomics_core-4.1.1.dist-info/METADATA
parsomics_core-4.1.1.dist-info/WHEEL
parsomics_core-4.1.1.dist-info/RECORD
