Metadata-Version: 2.1
Name: parsomics-core
Version: 4.1.1
Summary: A tool for parsing omics data into a relational database
License: GPL-3.0
Author: Pedro Sader Azevedo
Author-email: pedro.saderazevedo@lnbr.cnpem.br
Requires-Python: >=3.12,<4.0
Classifier: License :: OSI Approved :: GNU General Public License v3 (GPLv3)
Classifier: Programming Language :: Python :: 3
Classifier: Programming Language :: Python :: 3.12
Classifier: Programming Language :: Python :: 3.13
Requires-Dist: alembic (>=1.13.3,<2.0.0)
Requires-Dist: biopython (>=1.84,<2.0)
Requires-Dist: keyring (>=25.3.0,<26.0.0)
Requires-Dist: polars (>=1.6.0,<2.0.0)
Requires-Dist: psycopg2-binary (>=2.9.9,<3.0.0)
Requires-Dist: pydantic (>=2.9.0,<3.0.0)
Requires-Dist: sqlmodel (>=0.0.22,<0.0.23)
Requires-Dist: timeit-decorator (>=1.1.1,<2.0.0)
